{"Name":"C#","Posts":[{"Title":"C# features that Java doesn\u0027t have","Subtitle":null,"Slug":"csharp-features-java-doesnt-have","Author":null,"Image":null,"Published":"2023-04-14T00:00:00","EstimatedReadTime":"00:21:58.0363636","Excerpt":"\u003Cp\u003EIn this article I list some of the major features in C# and .NET that have no direct equivalent in Java. Some of the features are just mentioned because they are so essential and cool.\u003C/p\u003E\n\u003Cp\u003EI explain how stuff works and also demonstrate some in C# code.\u003C/p\u003E\n\u003Cp\u003EMy goal has been to show some C# specific syntax without highlighting it, like expression-bodied methods and alternative syntax for initializing objects. You will also notice my alternating use of \u003Ccode\u003Evar\u003C/code\u003E for type...","Tags":[".NET","C#"]},{"Title":"Introduction to .NET","Subtitle":null,"Slug":"introduction-to-dotnet","Author":"Marina Sundstr\u00F6m","Image":null,"Published":"2021-04-25T00:00:00","EstimatedReadTime":"00:04:22.6909090","Excerpt":"\u003Cp\u003E.NET is an open-source platform for building applications for the Web, Mobile, Desktop, and Cloud. Currently, it is at version 5, which was released in November 2020.\u003C/p\u003E\n\u003Cp\u003E.NET provides a runtime environment, the Common Language Runtime (CLR), an extensive base Base Class Library (BCL), programming languages like C#, VB.NET, and F#. On top of the platform you find many application frameworks, such as ASP.NET Core and WPF. It also integrates well with Microsoft Azure.\u003C/p\u003E\n\u003Cp\u003EThe platform...","Tags":[".NET","C#"]}],"Page":1,"TotalPages":1}